{
  "__inputs": [
    {
      "description": "",
      "label": "Prometheus",
      "name": "DS_PROMETHEUS",
      "pluginId": "prometheus",
      "pluginName": "Prometheus",
      "type": "datasource"
    }
  ],
  "__requires": [
    {
      "id": "grafana",
      "name": "Grafana",
      "type": "grafana",
      "version": "8.1.8"
    },
    {
      "id": "prometheus",
      "name": "Prometheus",
      "type": "datasource",
      "version": "1.0.0"
    },
    {
      "id": "table",
      "name": "Table",
      "type": "panel",
      "version": ""
    },
    {
      "id": "text",
      "name": "Text",
      "type": "panel",
      "version": ""
    },
    {
      "id": "timeseries",
      "name": "Time series",
      "type": "panel",
      "version": ""
    }
  ],
  "annotations": {
    "enable": false,
    "list": [
      {
        "builtIn": 1,
        "datasource": "-- Grafana --",
        "enable": true,
        "hide": true,
        "iconColor": "rgba(0, 211, 255, 1)",
        "name": "Annotations & Alerts",
        "target": {
          "limit": 100,
          "matchAny": false,
          "tags": [],
          "type": "dashboard"
        },
        "type": "dashboard"
      }
    ]
  },
  "description": "",
  "editable": true,
  "gnetId": null,
  "graphTooltip": 1,
  "id": null,
  "iteration": 1723188912328,
  "links": [
    {
      "asDropdown": true,
      "icon": "external link",
      "includeVars": true,
      "keepTime": true,
      "tags": [
        "cdot"
      ],
      "targetBlank": false,
      "title": "Related Dashboards",
      "tooltip": "",
      "type": "dashboards",
      "url": ""
    }
  ],
  "panels": [
    {
      "collapsed": false,
      "datasource": "${DS_PROMETHEUS}",
      "gridPos": {
        "h": 1,
        "w": 24,
        "x": 0,
        "y": 0
      },
      "id": 125,
      "panels": [],
      "title": "Important Information",
      "type": "row"
    },
    {
      "datasource": "${DS_PROMETHEUS}",
      "gridPos": {
        "h": 3,
        "w": 24,
        "x": 0,
        "y": 1
      },
      "id": 107,
      "options": {
        "content": "This dashboard requires ONTAP 9.7+. Three actions are required to use this dashboard: <br>1. If you are using the Rest collector, then you must enable the OntapS3 counters in `$HARVEST/conf/rest/default.yaml`. <br>2. If you are using the ZapiPerf collector, then you must enable the OntapS3SVM counters in `$HARVEST/conf/zapiperf/default.yaml`. <br>3. If you are using the RestPerf collector, then you must enable the OntapS3SVM counters in `$HARVEST/conf/restperf/default.yaml`. Please see https://github.com/NetApp/harvest/discussions/3137 for more details.",
        "mode": "markdown"
      },
      "pluginVersion": "8.1.8",
      "type": "text"
    },
    {
      "datasource": "${DS_PROMETHEUS}",
      "gridPos": {
        "h": 1,
        "w": 24,
        "x": 0,
        "y": 4
      },
      "id": 16,
      "title": "Bucket",
      "type": "row"
    },
    {
      "datasource": "${DS_PROMETHEUS}",
      "description": "You must enable the Rest collector in your harvest.yml config.",
      "fieldConfig": {
        "defaults": {
          "color": {
            "mode": "thresholds"
          },
          "custom": {
            "align": "auto",
            "displayMode": "auto",
            "filterable": true
          },
          "mappings": [],
          "thresholds": {
            "mode": "absolute",
            "steps": [
              {
                "color": "green",
                "value": null
              }
            ]
          },
          "unit": "bytes"
        },
        "overrides": [
          {
            "matcher": {
              "id": "byName",
              "options": "Free Size"
            },
            "properties": [
              {
                "id": "mappings",
                "value": [
                  {
                    "options": {
                      "from": -10000000000000000,
                      "result": {
                        "index": 0,
                        "text": "0 B"
                      },
                      "to": 0
                    },
                    "type": "range"
                  }
                ]
              }
            ]
          },
          {
            "matcher": {
              "id": "byName",
              "options": "Object Count"
            },
            "properties": [
              {
                "id": "unit",
                "value": "locale"
              }
            ]
          },
          {
            "matcher": {
              "id": "byName",
              "options": "Used %"
            },
            "properties": [
              {
                "id": "custom.displayMode",
                "value": "basic"
              },
              {
                "id": "decimals",
                "value": 0
              },
              {
                "id": "min",
                "value": 0
              },
              {
                "id": "max",
                "value": 100
              },
              {
                "id": "mappings",
                "value": [
                  {
                    "options": {
                      "from": 100,
                      "result": {
                        "index": 0,
                        "text": "100%"
                      },
                      "to": 999999
                    },
                    "type": "range"
                  }
                ]
              },
              {
                "id": "unit",
                "value": "percent"
              }
            ]
          },
          {
            "matcher": {
              "id": "byName",
              "options": "Encrypted"
            },
            "properties": [
              {
                "id": "mappings",
                "value": [
                  {
                    "options": {
                      "false": {
                        "index": 0,
                        "text": "No"
                      },
                      "true": {
                        "index": 1,
                        "text": "Yes"
                      }
                    },
                    "type": "value"
                  }
                ]
              }
            ]
          },
          {
            "matcher": {
              "id": "byName",
              "options": "cluster"
            },
            "properties": [
              {
                "id": "displayName",
                "value": "Cluster"
              },
              {
                "id": "links",
                "value": [
                  {
                    "targetBlank": true,
                    "title": "",
                    "url": "/d/cdot-cluster/ontap-cluster?orgId=1&${Datacenter:queryparam}&${__url_time_range}&var-Cluster=${__value.raw}"
                  }
                ]
              }
            ]
          },
          {
            "matcher": {
              "id": "byName",
              "options": "svm"
            },
            "properties": [
              {
                "id": "displayName",
                "value": "SVM"
              },
              {
                "id": "links",
                "value": [
                  {
                    "targetBlank": true,
                    "title": "",
                    "url": "/d/cdot-svm/ontap-svm?orgId=1&${Datacenter:queryparam}&${Cluster:queryparam}&${__url_time_range}&var-SVM=${__value.raw}"
                  }
                ]
              }
            ]
          },
          {
            "matcher": {
              "id": "byName",
              "options": "volume"
            },
            "properties": [
              {
                "id": "displayName",
                "value": "Volume"
              },
              {
                "id": "links",
                "value": [
                  {
                    "targetBlank": true,
                    "title": "",
                    "url": "/d/cdot-volume/ontap-volume?orgId=1&${Datacenter:queryparam}&${Cluster:queryparam}&${SVM:queryparam}&${__url_time_range}&var-Volume=${__value.raw}"
                  }
                ]
              }
            ]
          },
          {
            "matcher": {
              "id": "byName",
              "options": "datacenter"
            },
            "properties": [
              {
                "id": "displayName",
                "value": "Datacenter"
              },
              {
                "id": "links",
                "value": [
                  {
                    "targetBlank": true,
                    "title": "",
                    "url": "/d/cdot-datacenter/ontap-datacenter?orgId=1&${__url_time_range}&var-Datacenter=${__value.raw}"
                  }
                ]
              }
            ]
          }
        ]
      },
      "gridPos": {
        "h": 8,
        "w": 24,
        "x": 0,
        "y": 5
      },
      "id": 5,
      "options": {
        "footer": {
          "fields": "",
          "reducer": [
            "sum"
          ],
          "show": false
        },
        "showHeader": true
      },
      "pluginVersion": "8.1.8",
      "targets": [
        {
          "exemplar": false,
          "expr": "ontaps3_labels{datacenter=~\"$Datacenter\",cluster=~\"$Cluster\",svm=~\"$SVM\",bucket=~\"$Bucket\"} * on (volume,svm,cluster,datacenter) group_left(aggr) volume_labels{datacenter=~\"$Datacenter\",cluster=~\"$Cluster\",svm=~\"$SVM\"}",
          "format": "table",
          "hide": false,
          "instant": true,
          "interval": "",
          "legendFormat": "",
          "refId": "A"
        },
        {
          "exemplar": false,
          "expr": "ontaps3_size{datacenter=~\"$Datacenter\",cluster=~\"$Cluster\",svm=~\"$SVM\",bucket=~\"$Bucket\"}",
          "format": "table",
          "hide": false,
          "instant": true,
          "interval": "",
          "legendFormat": "",
          "refId": "B"
        },
        {
          "exemplar": false,
          "expr": "ontaps3_size-ontaps3_logical_used_size{datacenter=~\"$Datacenter\",cluster=~\"$Cluster\",svm=~\"$SVM\",bucket=~\"$Bucket\"}",
          "format": "table",
          "hide": false,
          "instant": true,
          "interval": "",
          "legendFormat": "",
          "refId": "C"
        },
        {
          "exemplar": false,
          "expr": "ontaps3_logical_used_size{datacenter=~\"$Datacenter\",cluster=~\"$Cluster\",svm=~\"$SVM\",bucket=~\"$Bucket\"}",
          "format": "table",
          "hide": false,
          "instant": true,
          "interval": "",
          "legendFormat": "",
          "refId": "D"
        },
        {
          "exemplar": false,
          "expr": "ontaps3_used_percent{datacenter=~\"$Datacenter\",cluster=~\"$Cluster\",svm=~\"$SVM\",bucket=~\"$Bucket\"}",
          "format": "table",
          "hide": false,
          "instant": true,
          "interval": "",
          "legendFormat": "",
          "refId": "E"
        },
        {
          "exemplar": false,
          "expr": "ontaps3_object_count{datacenter=~\"$Datacenter\",cluster=~\"$Cluster\",svm=~\"$SVM\",bucket=~\"$Bucket\"}",
          "format": "table",
          "hide": false,
          "instant": true,
          "interval": "",
          "legendFormat": "",
          "refId": "F"
        }
      ],
      "title": "Bucket Overview",
      "transformations": [
        {
          "id": "filterFieldsByName",
          "options": {
            "include": {
              "names": [
                "aggr",
                "bucket",
                "cluster",
                "encryption_enabled",
                "is_protected",
                "protected_in_cloud",
                "protected_in_ontap",
                "qos_policy_group",
                "svm",
                "url",
                "volume",
                "Value #B",
                "Value #C",
                "Value #D",
                "Value #E",
                "Value #F",
                "datacenter"
              ]
            }
          }
        },
        {
          "id": "merge",
          "options": {}
        },
        {
          "id": "organize",
          "options": {
            "excludeByName": {
              "Time": true,
              "__name__": true,
              "instance": true,
              "job": true
            },
            "indexByName": {
              "Value #B": 6,
              "Value #C": 7,
              "Value #D": 8,
              "Value #E": 9,
              "Value #F": 12,
              "aggr": 5,
              "bucket": 4,
              "cluster": 1,
              "datacenter": 0,
              "encryption_enabled": 11,
              "is_protected": 14,
              "protected_in_cloud": 15,
              "protected_in_ontap": 16,
              "qos_policy_group": 13,
              "svm": 2,
              "url": 10,
              "volume": 3
            },
            "renameByName": {
              "Value #A": "",
              "Value #B": "Size",
              "Value #C": "Free Size",
              "Value #D": "Used Size",
              "Value #E": "Used %",
              "Value #F": "Object Count",
              "aggr": "Local Tiers",
              "bucket": "Bucket",
              "encryption_enabled": "Encrypted",
              "is_protected": "IsProtected",
              "protected_in_cloud": "IsProtectedInCloud",
              "protected_in_ontap": "IsProtectedInOntap",
              "qos_policy_group": "QoS Policy Group",
              "url": "Url"
            }
          }
        }
      ],
      "type": "table"
    },
    {
      "datasource": "${DS_PROMETHEUS}",
      "description": "Specifies the bucket logical used size up to this point.",
      "fieldConfig": {
        "defaults": {
          "color": {
            "mode": "palette-classic"
          },
          "custom": {
            "axisLabel": "Used",
            "axisPlacement": "auto",
            "barAlignment": 0,
            "drawStyle": "line",
            "fillOpacity": 10,
            "gradientMode": "opacity",
            "hideFrom": {
              "legend": false,
              "tooltip": false,
              "viz": false
            },
            "lineInterpolation": "linear",
            "lineWidth": 1,
            "pointSize": 5,
            "scaleDistribution": {
              "type": "linear"
            },
            "showPoints": "auto",
            "spanNulls": true,
            "stacking": {
              "group": "A",
              "mode": "none"
            },
            "thresholdsStyle": {
              "mode": "off"
            }
          },
          "decimals": 2,
          "mappings": [],
          "thresholds": {
            "mode": "absolute",
            "steps": [
              {
                "color": "green",
                "value": null
              }
            ]
          },
          "unit": "bytes"
        },
        "overrides": []
      },
      "gridPos": {
        "h": 11,
        "w": 12,
        "x": 0,
        "y": 13
      },
      "id": 127,
      "options": {
        "legend": {
          "calcs": [
            "mean",
            "lastNotNull",
            "max"
          ],
          "displayMode": "table",
          "placement": "bottom",
          "sortBy": "Last *",
          "sortDesc": true
        },
        "tooltip": {
          "mode": "single",
          "sort": "none"
        }
      },
      "pluginVersion": "8.1.8",
      "targets": [
        {
          "datasource": "${DS_PROMETHEUS}",
          "exemplar": false,
          "expr": "ontaps3_logical_used_size{datacenter=~\"$Datacenter\",cluster=~\"$Cluster\",svm=~\"$SVM\",bucket=~\"$Bucket\"} \n  and \ntopk($TopResources, avg_over_time(ontaps3_logical_used_size{datacenter=~\"$Datacenter\",cluster=~\"$Cluster\",svm=~\"$SVM\",bucket=~\"$Bucket\"}[3h] @ end()))",
          "hide": false,
          "interval": "",
          "legendFormat": "{{svm}} - {{bucket}}",
          "refId": "A"
        }
      ],
      "title": "Top $TopResources Buckets by Used Size",
      "transformations": [],
      "type": "timeseries"
    },
    {
      "datasource": "${DS_PROMETHEUS}",
      "description": "Specifies the bucket logical used percent.",
      "fieldConfig": {
        "defaults": {
          "color": {
            "mode": "palette-classic"
          },
          "custom": {
            "axisLabel": "Used Percent %",
            "axisPlacement": "auto",
            "barAlignment": 0,
            "drawStyle": "line",
            "fillOpacity": 10,
            "gradientMode": "opacity",
            "hideFrom": {
              "legend": false,
              "tooltip": false,
              "viz": false
            },
            "lineInterpolation": "linear",
            "lineWidth": 1,
            "pointSize": 5,
            "scaleDistribution": {
              "type": "linear"
            },
            "showPoints": "auto",
            "spanNulls": true,
            "stacking": {
              "group": "A",
              "mode": "none"
            },
            "thresholdsStyle": {
              "mode": "off"
            }
          },
          "decimals": 2,
          "mappings": [],
          "max": 100,
          "min": 0,
          "thresholds": {
            "mode": "absolute",
            "steps": [
              {
                "color": "green",
                "value": null
              }
            ]
          },
          "unit": "percent"
        },
        "overrides": [
          {
            "matcher": {
              "id": "byName",
              "options": "Value"
            },
            "properties": [
              {
                "id": "mappings",
                "value": [
                  {
                    "options": {
                      "from": 100,
                      "result": {
                        "index": 0,
                        "text": "100%"
                      },
                      "to": 9999
                    },
                    "type": "range"
                  }
                ]
              }
            ]
          }
        ]
      },
      "gridPos": {
        "h": 11,
        "w": 12,
        "x": 12,
        "y": 13
      },
      "id": 128,
      "options": {
        "legend": {
          "calcs": [
            "mean",
            "lastNotNull",
            "max"
          ],
          "displayMode": "table",
          "placement": "bottom",
          "sortBy": "Last *",
          "sortDesc": true
        },
        "tooltip": {
          "mode": "single",
          "sort": "none"
        }
      },
      "pluginVersion": "8.1.8",
      "targets": [
        {
          "datasource": "${DS_PROMETHEUS}",
          "exemplar": false,
          "expr": "ontaps3_used_percent{datacenter=~\"$Datacenter\",cluster=~\"$Cluster\",svm=~\"$SVM\",bucket=~\"$Bucket\"} \n  and \ntopk($TopResources, avg_over_time(ontaps3_used_percent{datacenter=~\"$Datacenter\",cluster=~\"$Cluster\",svm=~\"$SVM\",bucket=~\"$Bucket\"}[3h] @ end()))",
          "hide": false,
          "interval": "",
          "legendFormat": "{{svm}} - {{bucket}}",
          "refId": "A"
        }
      ],
      "title": "Top $TopResources Buckets by Used Size Percent",
      "transformations": [],
      "type": "timeseries"
    },
    {
      "datasource": "${DS_PROMETHEUS}",
      "description": "You must enable the Rest collector in your harvest.yml config.",
      "fieldConfig": {
        "defaults": {
          "color": {
            "mode": "thresholds"
          },
          "custom": {
            "align": "auto",
            "displayMode": "auto",
            "filterable": true
          },
          "mappings": [],
          "thresholds": {
            "mode": "absolute",
            "steps": [
              {
                "color": "green",
                "value": null
              }
            ]
          }
        },
        "overrides": [
          {
            "matcher": {
              "id": "byName",
              "options": "User"
            },
            "properties": [
              {
                "id": "mappings",
                "value": [
                  {
                    "options": {
                      "match": "empty",
                      "result": {
                        "index": 0,
                        "text": "All users of this storage VM"
                      }
                    },
                    "type": "special"
                  }
                ]
              }
            ]
          },
          {
            "matcher": {
              "id": "byName",
              "options": "cluster"
            },
            "properties": [
              {
                "id": "displayName",
                "value": "Cluster"
              },
              {
                "id": "links",
                "value": [
                  {
                    "targetBlank": true,
                    "title": "",
                    "url": "/d/cdot-cluster/ontap-cluster?orgId=1&${Datacenter:queryparam}&${__url_time_range}&var-Cluster=${__value.raw}"
                  }
                ]
              }
            ]
          },
          {
            "matcher": {
              "id": "byName",
              "options": "svm"
            },
            "properties": [
              {
                "id": "displayName",
                "value": "SVM"
              },
              {
                "id": "links",
                "value": [
                  {
                    "targetBlank": true,
                    "title": "",
                    "url": "/d/cdot-svm/ontap-svm?orgId=1&${Datacenter:queryparam}&${Cluster:queryparam}&${__url_time_range}&var-SVM=${__value.raw}"
                  }
                ]
              }
            ]
          },
          {
            "matcher": {
              "id": "byName",
              "options": "datacenter"
            },
            "properties": [
              {
                "id": "displayName",
                "value": "Datacenter"
              },
              {
                "id": "links",
                "value": [
                  {
                    "targetBlank": true,
                    "title": "",
                    "url": "/d/cdot-datacenter/ontap-datacenter?orgId=1&${__url_time_range}&var-Datacenter=${__value.raw}"
                  }
                ]
              }
            ]
          }
        ]
      },
      "gridPos": {
        "h": 8,
        "w": 24,
        "x": 0,
        "y": 24
      },
      "id": 6,
      "options": {
        "footer": {
          "fields": "",
          "reducer": [
            "sum"
          ],
          "show": false
        },
        "showHeader": true,
        "sortBy": []
      },
      "pluginVersion": "8.1.8",
      "targets": [
        {
          "exemplar": false,
          "expr": "ontaps3_policy_labels{datacenter=~\"$Datacenter\",cluster=~\"$Cluster\",svm=~\"$SVM\",bucket=~\"$Bucket\",permission_type!=\"\"}",
          "format": "table",
          "hide": false,
          "instant": true,
          "interval": "",
          "legendFormat": "",
          "refId": "A"
        }
      ],
      "title": "Bucket Permission",
      "transformations": [
        {
          "id": "filterFieldsByName",
          "options": {
            "include": {
              "names": [
                "allowed_resource",
                "bucket",
                "cluster",
                "permission",
                "permission_type",
                "svm",
                "user",
                "datacenter"
              ]
            }
          }
        },
        {
          "id": "organize",
          "options": {
            "excludeByName": {},
            "indexByName": {
              "allowed_resource": 7,
              "bucket": 3,
              "cluster": 1,
              "datacenter": 0,
              "permission": 6,
              "permission_type": 5,
              "svm": 2,
              "user": 4
            },
            "renameByName": {
              "allowed_resource": "Allowed Resource",
              "bucket": "Bucket",
              "encryption_enabled": "",
              "permission": "Permission",
              "permission_type": "Type",
              "user": "User"
            }
          }
        }
      ],
      "type": "table"
    },
    {
      "collapsed": true,
      "datasource": "${DS_PROMETHEUS}",
      "gridPos": {
        "h": 1,
        "w": 24,
        "x": 0,
        "y": 32
      },
      "id": 17,
      "panels": [
        {
          "datasource": "${DS_PROMETHEUS}",
          "description": "This panel displays Requests and Connections counts at each SVM.",
          "fieldConfig": {
            "defaults": {
              "color": {
                "mode": "thresholds"
              },
              "custom": {
                "align": "auto",
                "cellOptions": {
                  "type": "auto"
                },
                "filterable": true,
                "inspect": false
              },
              "mappings": [],
              "thresholds": {
                "mode": "absolute",
                "steps": [
                  {
                    "color": "green",
                    "value": null
                  },
                  {
                    "color": "red",
                    "value": 80
                  }
                ]
              },
              "unit": "short",
              "unitScale": true
            },
            "overrides": [
              {
                "matcher": {
                  "id": "byName",
                  "options": "datacenter"
                },
                "properties": [
                  {
                    "id": "displayName",
                    "value": "Datacenter"
                  },
                  {
                    "id": "links",
                    "value": [
                      {
                        "targetBlank": true,
                        "title": "",
                        "url": "/d/cdot-datacenter/ontap-datacenter?orgId=1&${__url_time_range}&var-Datacenter=${__value.raw}"
                      }
                    ]
                  }
                ]
              },
              {
                "matcher": {
                  "id": "byName",
                  "options": "cluster"
                },
                "properties": [
                  {
                    "id": "displayName",
                    "value": "Cluster"
                  },
                  {
                    "id": "links",
                    "value": [
                      {
                        "targetBlank": true,
                        "title": "",
                        "url": "/d/cdot-cluster/ontap-cluster?orgId=1&${Datacenter:queryparam}&${__url_time_range}&var-Cluster=${__value.raw}"
                      }
                    ]
                  }
                ]
              },
              {
                "matcher": {
                  "id": "byName",
                  "options": "svm"
                },
                "properties": [
                  {
                    "id": "displayName",
                    "value": "SVM"
                  },
                  {
                    "id": "links",
                    "value": [
                      {
                        "targetBlank": true,
                        "title": "",
                        "url": "/d/cdot-svm/ontap-svm?orgId=1&${Datacenter:queryparam}&${Cluster:queryparam}&${__url_time_range}&var-SVM=${__value.raw}"
                      }
                    ]
                  }
                ]
              }
            ]
          },
          "gridPos": {
            "h": 10,
            "w": 24,
            "x": 0,
            "y": 5
          },
          "id": 137,
          "options": {
            "cellHeight": "sm",
            "footer": {
              "countRows": false,
              "fields": "",
              "reducer": [
                "sum"
              ],
              "show": false
            },
            "showHeader": true,
            "sortBy": [
              {
                "desc": false,
                "displayName": "SVM"
              }
            ]
          },
          "pluginVersion": "10.3.1",
          "targets": [
            {
              "editorMode": "code",
              "exemplar": false,
              "expr": "sum by (datacenter, cluster, svm)(ontaps3_svm_requests{datacenter=~\"$Datacenter\",cluster=~\"$Cluster\",svm=~\"$SVM\"})",
              "format": "table",
              "instant": true,
              "interval": "",
              "legendFormat": "",
              "refId": "A"
            },
            {
              "editorMode": "code",
              "exemplar": false,
              "expr": "sum by (datacenter, cluster, svm)(ontaps3_svm_connections{datacenter=~\"$Datacenter\",cluster=~\"$Cluster\",svm=~\"$SVM\"})",
              "format": "table",
              "hide": false,
              "instant": true,
              "interval": "",
              "legendFormat": "",
              "refId": "B"
            },
            {
              "editorMode": "code",
              "exemplar": false,
              "expr": "sum by (datacenter, cluster, svm)(ontaps3_svm_max_requests_outstanding{datacenter=~\"$Datacenter\",cluster=~\"$Cluster\",svm=~\"$SVM\"})",
              "format": "table",
              "hide": false,
              "instant": true,
              "interval": "",
              "legendFormat": "",
              "refId": "C"
            },
            {
              "editorMode": "code",
              "exemplar": false,
              "expr": "sum by (datacenter, cluster, svm)(ontaps3_svm_max_connected_connections{datacenter=~\"$Datacenter\",cluster=~\"$Cluster\",svm=~\"$SVM\"})",
              "format": "table",
              "hide": false,
              "instant": true,
              "interval": "",
              "legendFormat": "",
              "refId": "D"
            },
            {
              "editorMode": "code",
              "exemplar": false,
              "expr": "sum by (datacenter, cluster, svm)(ontaps3_svm_max_cmds_per_connection{datacenter=~\"$Datacenter\",cluster=~\"$Cluster\",svm=~\"$SVM\"})",
              "format": "table",
              "hide": false,
              "instant": true,
              "interval": "",
              "legendFormat": "",
              "refId": "E"
            }
          ],
          "title": "Requests & Connections stats",
          "transformations": [
            {
              "id": "filterFieldsByName",
              "options": {
                "include": {
                  "names": [
                    "Value #A",
                    "Value #B",
                    "Value #C",
                    "Value #D",
                    "Value #E",
                    "svm",
                    "cluster",
                    "datacenter"
                  ]
                }
              }
            },
            {
              "id": "merge",
              "options": {}
            },
            {
              "id": "organize",
              "options": {
                "excludeByName": {},
                "includeByName": {},
                "indexByName": {
                  "Value #A": 3,
                  "Value #B": 4,
                  "Value #C": 5,
                  "Value #D": 6,
                  "Value #E": 7,
                  "cluster": 1,
                  "datacenter": 0,
                  "svm": 2
                },
                "renameByName": {
                  "Value": "Used space",
                  "Value #A": "Requests",
                  "Value #B": "Connections",
                  "Value #C": "Max Outstanding Requests",
                  "Value #D": "Max Connected Connections",
                  "Value #E": "Max Commands Per Connections"
                }
              }
            }
          ],
          "type": "table"
        },
        {
          "datasource": "${DS_PROMETHEUS}",
          "description": "Number of GET/PUT/HEAD/DELETE SVM operations.",
          "fieldConfig": {
            "defaults": {
              "color": {
                "mode": "palette-classic"
              },
              "custom": {
                "axisBorderShow": false,
                "axisCenteredZero": false,
                "axisColorMode": "text",
                "axisLabel": "Operations",
                "axisPlacement": "auto",
                "barAlignment": 0,
                "drawStyle": "line",
                "fillOpacity": 10,
                "gradientMode": "opacity",
                "hideFrom": {
                  "legend": false,
                  "tooltip": false,
                  "viz": false
                },
                "insertNulls": false,
                "lineInterpolation": "linear",
                "lineWidth": 1,
                "pointSize": 5,
                "scaleDistribution": {
                  "type": "linear"
                },
                "showPoints": "auto",
                "spanNulls": true,
                "stacking": {
                  "group": "A",
                  "mode": "none"
                },
                "thresholdsStyle": {
                  "mode": "off"
                }
              },
              "mappings": [],
              "thresholds": {
                "mode": "absolute",
                "steps": [
                  {
                    "color": "green",
                    "value": null
                  }
                ]
              },
              "unit": "short",
              "unitScale": true
            },
            "overrides": []
          },
          "gridPos": {
            "h": 11,
            "w": 12,
            "x": 0,
            "y": 15
          },
          "id": 132,
          "options": {
            "legend": {
              "calcs": [
                "mean",
                "lastNotNull",
                "max"
              ],
              "displayMode": "table",
              "placement": "bottom",
              "showLegend": true,
              "sortBy": "Last *",
              "sortDesc": true
            },
            "tooltip": {
              "mode": "single",
              "sort": "none"
            }
          },
          "pluginVersion": "8.1.8",
          "targets": [
            {
              "editorMode": "code",
              "exemplar": false,
              "expr": "avg by(datacenter,cluster,svm)(ontaps3_svm_get_object_total{datacenter=~\"$Datacenter\",cluster=~\"$Cluster\",svm=~\"$SVM\"}) and topk($TopResources, avg by(datacenter,cluster,svm) (avg_over_time(ontaps3_svm_get_object_total{datacenter=~\"$Datacenter\",cluster=~\"$Cluster\",svm=~\"$SVM\"}[3h])))",
              "hide": false,
              "interval": "",
              "legendFormat": "{{svm}} - GET",
              "range": true,
              "refId": "A"
            },
            {
              "editorMode": "code",
              "exemplar": false,
              "expr": "avg by(datacenter,cluster,svm)(ontaps3_svm_put_object_total{datacenter=~\"$Datacenter\",cluster=~\"$Cluster\",svm=~\"$SVM\"}) and topk($TopResources, avg by(datacenter,cluster,svm) (avg_over_time(ontaps3_svm_put_object_total{datacenter=~\"$Datacenter\",cluster=~\"$Cluster\",svm=~\"$SVM\"}[3h])))",
              "hide": false,
              "interval": "",
              "legendFormat": "{{svm}} - PUT",
              "range": true,
              "refId": "B"
            },
            {
              "editorMode": "code",
              "exemplar": false,
              "expr": "avg by(datacenter,cluster,svm)(ontaps3_svm_head_object_total{datacenter=~\"$Datacenter\",cluster=~\"$Cluster\",svm=~\"$SVM\"}) and topk($TopResources, avg by(datacenter,cluster,svm) (avg_over_time(ontaps3_svm_head_object_total{datacenter=~\"$Datacenter\",cluster=~\"$Cluster\",svm=~\"$SVM\"}[3h])))",
              "hide": false,
              "interval": "",
              "legendFormat": "{{svm}} - HEAD",
              "range": true,
              "refId": "C"
            },
            {
              "editorMode": "code",
              "exemplar": false,
              "expr": "avg by(datacenter,cluster,svm)(ontaps3_svm_delete_object_total{datacenter=~\"$Datacenter\",cluster=~\"$Cluster\",svm=~\"$SVM\"}) and topk($TopResources, avg by(datacenter,cluster,svm) (avg_over_time(ontaps3_svm_delete_object_total{datacenter=~\"$Datacenter\",cluster=~\"$Cluster\",svm=~\"$SVM\"}[3h])))",
              "hide": false,
              "interval": "",
              "legendFormat": "{{svm}} - DELETE",
              "range": true,
              "refId": "D"
            }
          ],
          "title": "Top $TopResources SVMs by Operations",
          "transformations": [],
          "type": "timeseries"
        },
        {
          "datasource": "${DS_PROMETHEUS}",
          "description": "Number of GET/PUT/HEAD/DELETE SVM operations per second.",
          "fieldConfig": {
            "defaults": {
              "color": {
                "mode": "palette-classic"
              },
              "custom": {
                "axisBorderShow": false,
                "axisCenteredZero": false,
                "axisColorMode": "text",
                "axisLabel": "Operations/sec",
                "axisPlacement": "auto",
                "barAlignment": 0,
                "drawStyle": "line",
                "fillOpacity": 10,
                "gradientMode": "opacity",
                "hideFrom": {
                  "legend": false,
                  "tooltip": false,
                  "viz": false
                },
                "insertNulls": false,
                "lineInterpolation": "linear",
                "lineWidth": 1,
                "pointSize": 5,
                "scaleDistribution": {
                  "type": "linear"
                },
                "showPoints": "auto",
                "spanNulls": true,
                "stacking": {
                  "group": "A",
                  "mode": "none"
                },
                "thresholdsStyle": {
                  "mode": "off"
                }
              },
              "decimals": 0,
              "mappings": [],
              "thresholds": {
                "mode": "absolute",
                "steps": [
                  {
                    "color": "green",
                    "value": null
                  }
                ]
              },
              "unit": "iops",
              "unitScale": true
            },
            "overrides": []
          },
          "gridPos": {
            "h": 11,
            "w": 12,
            "x": 12,
            "y": 15
          },
          "id": 129,
          "options": {
            "legend": {
              "calcs": [
                "mean",
                "lastNotNull",
                "max"
              ],
              "displayMode": "table",
              "placement": "bottom",
              "showLegend": true,
              "sortBy": "Last *",
              "sortDesc": true
            },
            "tooltip": {
              "mode": "single",
              "sort": "none"
            }
          },
          "pluginVersion": "8.1.8",
          "targets": [
            {
              "editorMode": "code",
              "exemplar": false,
              "expr": "avg by(datacenter,cluster,svm)(ontaps3_svm_get_object_rate{datacenter=~\"$Datacenter\",cluster=~\"$Cluster\",svm=~\"$SVM\"}) and topk($TopResources, avg by(datacenter,cluster,svm) (avg_over_time(ontaps3_svm_get_object_rate{datacenter=~\"$Datacenter\",cluster=~\"$Cluster\",svm=~\"$SVM\"}[3h])))",
              "hide": false,
              "interval": "",
              "legendFormat": "{{svm}} - GET",
              "range": true,
              "refId": "A"
            },
            {
              "editorMode": "code",
              "exemplar": false,
              "expr": "avg by(datacenter,cluster,svm)(ontaps3_svm_put_object_rate{datacenter=~\"$Datacenter\",cluster=~\"$Cluster\",svm=~\"$SVM\"}) and topk($TopResources, avg by(datacenter,cluster,svm) (avg_over_time(ontaps3_svm_put_object_rate{datacenter=~\"$Datacenter\",cluster=~\"$Cluster\",svm=~\"$SVM\"}[3h])))",
              "hide": false,
              "interval": "",
              "legendFormat": "{{svm}} - PUT",
              "range": true,
              "refId": "B"
            },
            {
              "editorMode": "code",
              "exemplar": false,
              "expr": "avg by(datacenter,cluster,svm)(ontaps3_svm_head_object_rate{datacenter=~\"$Datacenter\",cluster=~\"$Cluster\",svm=~\"$SVM\"}) and topk($TopResources, avg by(datacenter,cluster,svm) (avg_over_time(ontaps3_svm_head_object_rate{datacenter=~\"$Datacenter\",cluster=~\"$Cluster\",svm=~\"$SVM\"}[3h])))",
              "hide": false,
              "interval": "",
              "legendFormat": "{{svm}} - HEAD",
              "range": true,
              "refId": "C"
            },
            {
              "editorMode": "code",
              "exemplar": false,
              "expr": "avg by(datacenter,cluster,svm)(ontaps3_svm_delete_object_rate{datacenter=~\"$Datacenter\",cluster=~\"$Cluster\",svm=~\"$SVM\"}) and topk($TopResources, avg by(datacenter,cluster,svm) (avg_over_time(ontaps3_svm_delete_object_rate{datacenter=~\"$Datacenter\",cluster=~\"$Cluster\",svm=~\"$SVM\"}[3h])))",
              "hide": false,
              "interval": "",
              "legendFormat": "{{svm}} - DELETE",
              "range": true,
              "refId": "D"
            }
          ],
          "title": "Top $TopResources SVMs by Rate",
          "transformations": [],
          "type": "timeseries"
        },
        {
          "datasource": "${DS_PROMETHEUS}",
          "description": "Average latency for GET/PUT/HEAD/DELETE SVM operations.",
          "fieldConfig": {
            "defaults": {
              "color": {
                "mode": "palette-classic"
              },
              "custom": {
                "axisBorderShow": false,
                "axisCenteredZero": false,
                "axisColorMode": "text",
                "axisLabel": "Latency",
                "axisPlacement": "auto",
                "barAlignment": 0,
                "drawStyle": "line",
                "fillOpacity": 10,
                "gradientMode": "opacity",
                "hideFrom": {
                  "legend": false,
                  "tooltip": false,
                  "viz": false
                },
                "insertNulls": false,
                "lineInterpolation": "linear",
                "lineWidth": 1,
                "pointSize": 5,
                "scaleDistribution": {
                  "type": "linear"
                },
                "showPoints": "auto",
                "spanNulls": true,
                "stacking": {
                  "group": "A",
                  "mode": "none"
                },
                "thresholdsStyle": {
                  "mode": "off"
                }
              },
              "mappings": [],
              "thresholds": {
                "mode": "absolute",
                "steps": [
                  {
                    "color": "green",
                    "value": null
                  }
                ]
              },
              "unit": "µs",
              "unitScale": true
            },
            "overrides": []
          },
          "gridPos": {
            "h": 11,
            "w": 12,
            "x": 0,
            "y": 26
          },
          "id": 130,
          "options": {
            "legend": {
              "calcs": [
                "mean",
                "lastNotNull",
                "max"
              ],
              "displayMode": "table",
              "placement": "bottom",
              "showLegend": true,
              "sortBy": "Last *",
              "sortDesc": true
            },
            "tooltip": {
              "mode": "single",
              "sort": "none"
            }
          },
          "pluginVersion": "8.1.8",
          "targets": [
            {
              "editorMode": "code",
              "exemplar": false,
              "expr": "avg by(datacenter,cluster,svm)(ontaps3_svm_get_object_latency{datacenter=~\"$Datacenter\",cluster=~\"$Cluster\",svm=~\"$SVM\"}) and topk($TopResources, avg by(datacenter,cluster,svm) (avg_over_time(ontaps3_svm_get_object_latency{datacenter=~\"$Datacenter\",cluster=~\"$Cluster\",svm=~\"$SVM\"}[3h])))",
              "hide": false,
              "interval": "",
              "legendFormat": "{{svm}} - GET",
              "range": true,
              "refId": "A"
            },
            {
              "editorMode": "code",
              "exemplar": false,
              "expr": "avg by(datacenter,cluster,svm)(ontaps3_svm_put_object_latency{datacenter=~\"$Datacenter\",cluster=~\"$Cluster\",svm=~\"$SVM\"}) and topk($TopResources, avg by(datacenter,cluster,svm) (avg_over_time(ontaps3_svm_put_object_latency{datacenter=~\"$Datacenter\",cluster=~\"$Cluster\",svm=~\"$SVM\"}[3h])))",
              "hide": false,
              "interval": "",
              "legendFormat": "{{svm}} - PUT",
              "range": true,
              "refId": "B"
            },
            {
              "editorMode": "code",
              "exemplar": false,
              "expr": "avg by(datacenter,cluster,svm)(ontaps3_svm_head_object_latency{datacenter=~\"$Datacenter\",cluster=~\"$Cluster\",svm=~\"$SVM\"}) and topk($TopResources, avg by(datacenter,cluster,svm) (avg_over_time(ontaps3_svm_head_object_latency{datacenter=~\"$Datacenter\",cluster=~\"$Cluster\",svm=~\"$SVM\"}[3h])))",
              "hide": false,
              "interval": "",
              "legendFormat": "{{svm}} - HEAD",
              "range": true,
              "refId": "C"
            },
            {
              "editorMode": "code",
              "exemplar": false,
              "expr": "avg by(datacenter,cluster,svm)(ontaps3_svm_delete_object_latency{datacenter=~\"$Datacenter\",cluster=~\"$Cluster\",svm=~\"$SVM\"}) and topk($TopResources, avg by(datacenter,cluster,svm) (avg_over_time(ontaps3_svm_delete_object_latency{datacenter=~\"$Datacenter\",cluster=~\"$Cluster\",svm=~\"$SVM\"}[3h])))",
              "hide": false,
              "interval": "",
              "legendFormat": "{{svm}} - DELETE",
              "range": true,
              "refId": "D"
            }
          ],
          "title": "Top $TopResources SVMs by Latency",
          "transformations": [],
          "type": "timeseries"
        },
        {
          "datasource": "${DS_PROMETHEUS}",
          "description": "Rate of GET/PUT SVM data transfers per second.",
          "fieldConfig": {
            "defaults": {
              "color": {
                "mode": "palette-classic"
              },
              "custom": {
                "axisBorderShow": false,
                "axisCenteredZero": false,
                "axisColorMode": "text",
                "axisLabel": "Data Transfer",
                "axisPlacement": "auto",
                "barAlignment": 0,
                "drawStyle": "line",
                "fillOpacity": 10,
                "gradientMode": "opacity",
                "hideFrom": {
                  "legend": false,
                  "tooltip": false,
                  "viz": false
                },
                "insertNulls": false,
                "lineInterpolation": "linear",
                "lineWidth": 1,
                "pointSize": 5,
                "scaleDistribution": {
                  "type": "linear"
                },
                "showPoints": "auto",
                "spanNulls": true,
                "stacking": {
                  "group": "A",
                  "mode": "none"
                },
                "thresholdsStyle": {
                  "mode": "off"
                }
              },
              "decimals": 2,
              "mappings": [],
              "thresholds": {
                "mode": "absolute",
                "steps": [
                  {
                    "color": "green",
                    "value": null
                  }
                ]
              },
              "unit": "bytes",
              "unitScale": true
            },
            "overrides": []
          },
          "gridPos": {
            "h": 11,
            "w": 12,
            "x": 12,
            "y": 26
          },
          "id": 131,
          "options": {
            "legend": {
              "calcs": [
                "mean",
                "lastNotNull",
                "max"
              ],
              "displayMode": "table",
              "placement": "bottom",
              "showLegend": true,
              "sortBy": "Last *",
              "sortDesc": true
            },
            "tooltip": {
              "mode": "single",
              "sort": "none"
            }
          },
          "pluginVersion": "8.1.8",
          "targets": [
            {
              "editorMode": "code",
              "exemplar": false,
              "expr": "avg by(datacenter,cluster,svm)(ontaps3_svm_get_data{datacenter=~\"$Datacenter\",cluster=~\"$Cluster\",svm=~\"$SVM\"}) and topk($TopResources, avg by(datacenter,cluster,svm) (avg_over_time(ontaps3_svm_get_data{datacenter=~\"$Datacenter\",cluster=~\"$Cluster\",svm=~\"$SVM\"}[3h])))",
              "hide": false,
              "interval": "",
              "legendFormat": "{{svm}} - GET",
              "range": true,
              "refId": "A"
            },
            {
              "editorMode": "code",
              "exemplar": false,
              "expr": "avg by(datacenter,cluster,svm)(ontaps3_svm_put_data{datacenter=~\"$Datacenter\",cluster=~\"$Cluster\",svm=~\"$SVM\"}) and topk($TopResources, avg by(datacenter,cluster,svm) (avg_over_time(ontaps3_svm_put_data{datacenter=~\"$Datacenter\",cluster=~\"$Cluster\",svm=~\"$SVM\"}[3h])))",
              "hide": false,
              "interval": "",
              "legendFormat": "{{svm}} - PUT",
              "range": true,
              "refId": "B"
            }
          ],
          "title": "Top $TopResources SVMs by Data Transfer",
          "transformations": [],
          "type": "timeseries"
        }
      ],
      "title": "S3 Object Storage SVM",
      "type": "row"
    }
  ],
  "refresh": "",
  "schemaVersion": 30,
  "style": "dark",
  "tags": [
    "harvest",
    "ontap",
    "cdot"
  ],
  "templating": {
    "list": [
      {
        "current": {
          "selected": false,
          "text": "Prometheus",
          "value": "Prometheus"
        },
        "description": null,
        "error": null,
        "hide": 2,
        "includeAll": false,
        "label": "Data Source",
        "multi": false,
        "name": "DS_PROMETHEUS",
        "options": [],
        "query": "prometheus",
        "refresh": 2,
        "regex": "",
        "skipUrlSync": false,
        "type": "datasource"
      },
      {
        "allValue": null,
        "current": {},
        "datasource": "${DS_PROMETHEUS}",
        "definition": "label_values(ontaps3_labels{system_type!=\"7mode\"}, datacenter)",
        "description": null,
        "error": null,
        "hide": 0,
        "includeAll": false,
        "label": null,
        "multi": true,
        "name": "Datacenter",
        "options": [],
        "query": {
          "query": "label_values(ontaps3_labels{system_type!=\"7mode\"}, datacenter)",
          "refId": "StandardVariableQuery"
        },
        "refresh": 2,
        "regex": "",
        "skipUrlSync": false,
        "sort": 1,
        "tagValuesQuery": "",
        "tags": [],
        "tagsQuery": "",
        "type": "query",
        "useTags": false
      },
      {
        "allValue": ".*",
        "current": {},
        "datasource": "${DS_PROMETHEUS}",
        "definition": "label_values(ontaps3_labels{system_type!=\"7mode\",datacenter=~\"$Datacenter\"}, cluster)",
        "description": null,
        "error": null,
        "hide": 0,
        "includeAll": true,
        "label": null,
        "multi": true,
        "multiFormat": "glob",
        "name": "Cluster",
        "options": [],
        "query": {
          "query": "label_values(ontaps3_labels{system_type!=\"7mode\",datacenter=~\"$Datacenter\"}, cluster)",
          "refId": "StandardVariableQuery"
        },
        "refresh": 2,
        "refresh_on_load": false,
        "regex": "",
        "skipUrlSync": false,
        "sort": 1,
        "type": "query"
      },
      {
        "allValue": ".*",
        "current": {},
        "datasource": "${DS_PROMETHEUS}",
        "definition": "label_values(ontaps3_labels{datacenter=~\"$Datacenter\",cluster=~\"$Cluster\"}, svm)",
        "description": null,
        "error": null,
        "hide": 0,
        "includeAll": true,
        "label": null,
        "multi": true,
        "multiFormat": "glob",
        "name": "SVM",
        "options": [],
        "query": {
          "query": "label_values(ontaps3_labels{datacenter=~\"$Datacenter\",cluster=~\"$Cluster\"}, svm)",
          "refId": "StandardVariableQuery"
        },
        "refresh": 2,
        "refresh_on_load": false,
        "regex": "",
        "skipUrlSync": false,
        "sort": 1,
        "type": "query"
      },
      {
        "allValue": ".*",
        "current": {},
        "datasource": "${DS_PROMETHEUS}",
        "definition": "label_values(ontaps3_labels{datacenter=~\"$Datacenter\",cluster=~\"$Cluster\", svm=~\"$SVM\"}, bucket)",
        "description": null,
        "error": null,
        "hide": 0,
        "includeAll": true,
        "label": null,
        "multi": true,
        "multiFormat": "glob",
        "name": "Bucket",
        "options": [],
        "query": {
          "query": "label_values(ontaps3_labels{datacenter=~\"$Datacenter\",cluster=~\"$Cluster\", svm=~\"$SVM\"}, bucket)",
          "refId": "StandardVariableQuery"
        },
        "refresh": 2,
        "refresh_on_load": false,
        "regex": "",
        "skipUrlSync": false,
        "sort": 1,
        "type": "query"
      },
      {
        "allValue": null,
        "current": {
          "selected": true,
          "text": "5",
          "value": "5"
        },
        "description": null,
        "error": null,
        "hide": 0,
        "includeAll": false,
        "label": null,
        "multi": false,
        "name": "TopResources",
        "options": [
          {
            "selected": false,
            "text": "1",
            "value": "1"
          },
          {
            "selected": false,
            "text": "2",
            "value": "2"
          },
          {
            "selected": false,
            "text": "3",
            "value": "3"
          },
          {
            "selected": false,
            "text": "4",
            "value": "4"
          },
          {
            "selected": true,
            "text": "5",
            "value": "5"
          },
          {
            "selected": false,
            "text": "6",
            "value": "6"
          },
          {
            "selected": false,
            "text": "8",
            "value": "8"
          },
          {
            "selected": false,
            "text": "10",
            "value": "10"
          },
          {
            "selected": false,
            "text": "15",
            "value": "15"
          },
          {
            "selected": false,
            "text": "25",
            "value": "25"
          },
          {
            "selected": false,
            "text": "50",
            "value": "50"
          },
          {
            "selected": false,
            "text": "100",
            "value": "100"
          },
          {
            "selected": false,
            "text": "250",
            "value": "250"
          },
          {
            "selected": false,
            "text": "500",
            "value": "500"
          }
        ],
        "query": "1,2,3,4,5,6,8,10,15,25,50,100,250,500",
        "queryValue": "",
        "skipUrlSync": false,
        "type": "custom"
      }
    ]
  },
  "time": {
    "from": "now-3h",
    "to": "now"
  },
  "timepicker": {
    "refresh_intervals": [
      "10s",
      "30s",
      "1m",
      "5m",
      "15m",
      "30m",
      "1h",
      "2h",
      "1d"
    ]
  },
  "timezone": "",
  "title": "ONTAP: S3 Object Storage",
  "uid": "cdot-s3-object-storage",
  "version": 2
}
